{
    "season": "1928-29",
    "next": "1929-30",
    "prev": "1927-28",
    "league": [{
        "level": 1,
        "name": "1. Division",
        "pts_win": 2,
        "standings": [
            {"place": 1, "team": "SPOR", "w": 7, "d": 5, "l":  2, "f": 42, "a": 22, "pts_win": 2, "season": "1928-29", "competition": {"type":"league","level": 1, "league": "1. Division"}, "champion": true},
            {"place": 2, "team": "FOLA", "w": 8, "d": 2, "l":  4, "f": 33, "a": 32, "pts_win": 2, "season": "1928-29", "competition": {"type":"league","level": 1, "league": "1. Division"}},
            {"place": 3, "team": "RBDF", "w": 6, "d": 5, "l":  3, "f": 33, "a": 19, "pts_win": 2, "season": "1928-29", "competition": {"type":"league","level": 1, "league": "1. Division"}},
            {"place": 4, "team": "JESH", "w": 6, "d": 3, "l":  5, "f": 27, "a": 27, "pts_win": 2, "season": "1928-29", "competition": {"type":"league","level": 1, "league": "1. Division"}},
            {"place": 5, "team": "PRON", "w": 5, "d": 4, "l":  5, "f": 33, "a": 34, "pts_win": 2, "season": "1928-29", "competition": {"type":"league","level": 1, "league": "1. Division"}},
            {"place": 6, "team": "RBPF", "w": 4, "d": 5, "l":  5, "f": 20, "a": 25, "pts_win": 2, "season": "1928-29", "competition": {"type":"league","level": 1, "league": "1. Division"}},
            {"place": 7, "team": "ASDF", "w": 4, "d": 3, "l":  7, "f": 22, "a": 29, "pts_win": 2, "season": "1928-29", "competition": {"type":"league","level": 1, "league": "1. Division"}, "relegated": true},
            {"place": 8, "team": "SDUD", "w": 1, "d": 3, "l": 10, "f": 19, "a": 41, "pts_win": 2, "season": "1928-29", "competition": {"type":"league","level": 1, "league": "1. Division"}, "relegated": true}
        ],
        "matches": [
            {"home":"SPOR","away":"FOLA","score":"6-1","season":"1928-29","competition":{"type":"league","level": 1,"league": "1. Division"}},
            {"home":"SPOR","away":"RBDF","score":"2-2","season":"1928-29","competition":{"type":"league","level": 1,"league": "1. Division"}},
            {"home":"SPOR","away":"JESH","score":"4-2","season":"1928-29","competition":{"type":"league","level": 1,"league": "1. Division"}},
            {"home":"SPOR","away":"PRON","score":"7-1","season":"1928-29","competition":{"type":"league","level": 1,"league": "1. Division"}},
            {"home":"SPOR","away":"RBPF","score":"1-1","season":"1928-29","competition":{"type":"league","level": 1,"league": "1. Division"}},
            {"home":"SPOR","away":"ASDF","score":"3-0","season":"1928-29","competition":{"type":"league","level": 1,"league": "1. Division"}},
            {"home":"SPOR","away":"SDUD","score":"4-1","season":"1928-29","competition":{"type":"league","level": 1,"league": "1. Division"}},
            {"home":"FOLA","away":"SPOR","score":"3-1","season":"1928-29","competition":{"type":"league","level": 1,"league": "1. Division"}},
            {"home":"FOLA","away":"RBDF","score":"2-2","season":"1928-29","competition":{"type":"league","level": 1,"league": "1. Division"}},
            {"home":"FOLA","away":"JESH","score":"3-2","season":"1928-29","competition":{"type":"league","level": 1,"league": "1. Division"}},
            {"home":"FOLA","away":"PRON","score":"4-3","season":"1928-29","competition":{"type":"league","level": 1,"league": "1. Division"}},
            {"home":"FOLA","away":"RBPF","score":"1-2","season":"1928-29","competition":{"type":"league","level": 1,"league": "1. Division"}},
            {"home":"FOLA","away":"ASDF","score":"4-1","season":"1928-29","competition":{"type":"league","level": 1,"league": "1. Division"}},
            {"home":"FOLA","away":"SDUD","score":"3-1","season":"1928-29","competition":{"type":"league","level": 1,"league": "1. Division"}},
            {"home":"RBDF","away":"SPOR","score":"1-1","season":"1928-29","competition":{"type":"league","level": 1,"league": "1. Division"}},
            {"home":"RBDF","away":"FOLA","score":"4-0","season":"1928-29","competition":{"type":"league","level": 1,"league": "1. Division"}},
            {"home":"RBDF","away":"JESH","score":"5-2","season":"1928-29","competition":{"type":"league","level": 1,"league": "1. Division"}},
            {"home":"RBDF","away":"PRON","score":"1-3","season":"1928-29","competition":{"type":"league","level": 1,"league": "1. Division"}},
            {"home":"RBDF","away":"RBPF","score":"4-0","season":"1928-29","competition":{"type":"league","level": 1,"league": "1. Division"}},
            {"home":"RBDF","away":"ASDF","score":"1-1","season":"1928-29","competition":{"type":"league","level": 1,"league": "1. Division"}},
            {"home":"RBDF","away":"SDUD","score":"5-1","season":"1928-29","competition":{"type":"league","level": 1,"league": "1. Division"}},
            {"home":"JESH","away":"SPOR","score":"1-1","season":"1928-29","competition":{"type":"league","level": 1,"league": "1. Division"}},
            {"home":"JESH","away":"FOLA","score":"2-1","season":"1928-29","competition":{"type":"league","level": 1,"league": "1. Division"}},
            {"home":"JESH","away":"RBDF","score":"2-1","season":"1928-29","competition":{"type":"league","level": 1,"league": "1. Division"}},
            {"home":"JESH","away":"PRON","score":"3-1","season":"1928-29","competition":{"type":"league","level": 1,"league": "1. Division"}},
            {"home":"JESH","away":"RBPF","score":"2-2","season":"1928-29","competition":{"type":"league","level": 1,"league": "1. Division"}},
            {"home":"JESH","away":"ASDF","score":"1-1","season":"1928-29","competition":{"type":"league","level": 1,"league": "1. Division"}},
            {"home":"JESH","away":"SDUD","score":"2-0","season":"1928-29","competition":{"type":"league","level": 1,"league": "1. Division"}},
            {"home":"PRON","away":"SPOR","score":"2-4","season":"1928-29","competition":{"type":"league","level": 1,"league": "1. Division"}},
            {"home":"PRON","away":"FOLA","score":"2-2","season":"1928-29","competition":{"type":"league","level": 1,"league": "1. Division"}},
            {"home":"PRON","away":"RBDF","score":"4-3","season":"1928-29","competition":{"type":"league","level": 1,"league": "1. Division"}},
            {"home":"PRON","away":"JESH","score":"4-1","season":"1928-29","competition":{"type":"league","level": 1,"league": "1. Division"}},
            {"home":"PRON","away":"RBPF","score":"1-2","season":"1928-29","competition":{"type":"league","level": 1,"league": "1. Division"}},
            {"home":"PRON","away":"ASDF","score":"2-2","season":"1928-29","competition":{"type":"league","level": 1,"league": "1. Division"}},
            {"home":"PRON","away":"SDUD","score":"0-0","season":"1928-29","competition":{"type":"league","level": 1,"league": "1. Division"}},
            {"home":"RBPF","away":"SPOR","score":"2-2","season":"1928-29","competition":{"type":"league","level": 1,"league": "1. Division"}},
            {"home":"RBPF","away":"FOLA","score":"1-2","season":"1928-29","competition":{"type":"league","level": 1,"league": "1. Division"}},
            {"home":"RBPF","away":"RBDF","score":"0-2","season":"1928-29","competition":{"type":"league","level": 1,"league": "1. Division"}},
            {"home":"RBPF","away":"JESH","score":"1-2","season":"1928-29","competition":{"type":"league","level": 1,"league": "1. Division"}},
            {"home":"RBPF","away":"PRON","score":"2-2","season":"1928-29","competition":{"type":"league","level": 1,"league": "1. Division"}},
            {"home":"RBPF","away":"ASDF","score":"2-0","season":"1928-29","competition":{"type":"league","level": 1,"league": "1. Division"}},
            {"home":"RBPF","away":"SDUD","score":"2-0","season":"1928-29","competition":{"type":"league","level": 1,"league": "1. Division"}},
            {"home":"ASDF","away":"SPOR","score":"2-4","season":"1928-29","competition":{"type":"league","level": 1,"league": "1. Division"}},
            {"home":"ASDF","away":"FOLA","score":"2-3","season":"1928-29","competition":{"type":"league","level": 1,"league": "1. Division"}},
            {"home":"ASDF","away":"RBDF","score":"0-1","season":"1928-29","competition":{"type":"league","level": 1,"league": "1. Division"}},
            {"home":"ASDF","away":"JESH","score":"2-0","season":"1928-29","competition":{"type":"league","level": 1,"league": "1. Division"}},
            {"home":"ASDF","away":"PRON","score":"1-5","season":"1928-29","competition":{"type":"league","level": 1,"league": "1. Division"}},
            {"home":"ASDF","away":"RBPF","score":"3-0","season":"1928-29","competition":{"type":"league","level": 1,"league": "1. Division"},"forfeit":true},
            {"home":"ASDF","away":"SDUD","score":"3-1","season":"1928-29","competition":{"type":"league","level": 1,"league": "1. Division"}},
            {"home":"SDUD","away":"SPOR","score":"3-2","season":"1928-29","competition":{"type":"league","level": 1,"league": "1. Division"}},
            {"home":"SDUD","away":"FOLA","score":"3-4","season":"1928-29","competition":{"type":"league","level": 1,"league": "1. Division"}},
            {"home":"SDUD","away":"RBDF","score":"1-1","season":"1928-29","competition":{"type":"league","level": 1,"league": "1. Division"}},
            {"home":"SDUD","away":"JESH","score":"1-5","season":"1928-29","competition":{"type":"league","level": 1,"league": "1. Division"}},
            {"home":"SDUD","away":"PRON","score":"2-3","season":"1928-29","competition":{"type":"league","level": 1,"league": "1. Division"}},
            {"home":"SDUD","away":"RBPF","score":"3-3","season":"1928-29","competition":{"type":"league","level": 1,"league": "1. Division"}},
            {"home":"SDUD","away":"ASDF","score":"2-4","season":"1928-29","competition":{"type":"league","level": 1,"league": "1. Division"}}
        ]
    },{
        "level": 2,
        "name": "The Promotion",
        "pts_win": 2,
        "standings": [
            {"place": 1, "team": "ULUX", "w": 12, "d": 0, "l":  2, "f": 66, "a": 27, "pts_win": 2, "season": "1928-29", "competition":{"type":"league","level": 2, "league": "The Promotion"}, "promoted": true},
            {"place": 2, "team": "USDD", "w":  9, "d": 2, "l":  3, "f": 50, "a": 22, "pts_win": 2, "season": "1928-29", "competition":{"type":"league","level": 2, "league": "The Promotion"}, "promoted": true},
            {"place": 3, "team": "ARIS", "w":  8, "d": 1, "l":  5, "f": 34, "a": 28, "pts_win": 2, "season": "1928-29", "competition":{"type":"league","level": 2, "league": "The Promotion"}},
            {"place": 4, "team": "PROG", "w":  7, "d": 1, "l":  6, "f": 42, "a": 31, "pts_win": 2, "season": "1928-29", "competition":{"type":"league","level": 2, "league": "The Promotion"}},
            {"place": 5, "team": "NSCH", "w":  6, "d": 3, "l":  5, "f": 38, "a": 32, "pts_win": 2, "season": "1928-29", "competition":{"type":"league","level": 2, "league": "The Promotion"}},
            {"place": 6, "team": "ADUD", "w":  6, "d": 0, "l":  8, "f": 32, "a": 47, "pts_win": 2, "season": "1928-29", "competition":{"type":"league","level": 2, "league": "The Promotion"}},
            {"place": 7, "team": "CPET", "w":  1, "d": 3, "l": 10, "f": 18, "a": 56, "pts_win": 2, "season": "1928-29", "competition":{"type":"league","level": 2, "league": "The Promotion"}, "relegated": true},
            {"place": 8, "team": "SWFT", "w":  1, "d": 2, "l": 11, "f": 30, "a": 67, "pts_win": 2, "season": "1928-29", "competition":{"type":"league","level": 2, "league": "The Promotion"}, "relegated": true}
        ]
    },{
        "level": 3,
        "name": "2. Division",
        "pts_win": 2,
        "series": [{
            "serie": 1,
            "name": "Series 1",
            "pts_win": 2,
            "standings": [
                {"place": 1, "team": "SPST", "w": 9, "d": 3, "l":  2, "f": 39, "a": 23, "pts_win": 2, "season": "1928-29", "competition": {"type":"league_series","level": 3, "series":1, "league": "2. Division Series 1"}, "promoted": true},
                {"place": 2, "team": "AVBG", "w": 9, "d": 2, "l":  3, "f": 53, "a": 16, "pts_win": 2, "season": "1928-29", "competition": {"type":"league_series","level": 3, "series":1, "league": "2. Division Series 1"}},
                {"place": 3, "team": "ETZE", "w": 8, "d": 4, "l":  2, "f": 48, "a": 34, "pts_win": 2, "season": "1928-29", "competition": {"type":"league_series","level": 3, "series":1, "league": "2. Division Series 1"}},
                {"place": 4, "team": "YBDK", "w": 6, "d": 1, "l":  7, "f": 32, "a": 33, "pts_win": 2, "season": "1928-29", "competition": {"type":"league_series","level": 3, "series":1, "league": "2. Division Series 1"}},
                {"place": 5, "team": "EGWM", "w": 5, "d": 3, "l":  6, "f": 30, "a": 20, "pts_win": 2, "season": "1928-29", "competition": {"type":"league_series","level": 3, "series":1, "league": "2. Division Series 1"}},
                {"place": 6, "team": "GOLD", "w": 5, "d": 3, "l":  6, "f": 30, "a": 22, "pts_win": 2, "season": "1928-29", "competition": {"type":"league_series","level": 3, "series":1, "league": "2. Division Series 1"}},
                {"place": 7, "team": "USND", "w": 5, "d": 2, "l":  7, "f": 29, "a": 33, "pts_win": 2, "season": "1928-29", "competition": {"type":"league_series","level": 3, "series":1, "league": "2. Division Series 1"}},
                {"place": 8, "team": "MANC", "w": 0, "d": 0, "l": 14, "f": 13, "a": 93, "pts_win": 2, "season": "1928-29", "competition": {"type":"league_series","level": 3, "series":1, "league": "2. Division Series 1"}, "relegated": true}
            ]
        },{
            "serie": 2,
            "name": "Series 2",
            "pts_win": 2,
            "standings": [
                {"place": 1, "team": "URUM", "w": 10, "d": 2, "l":  2, "f": 46, "a": 19, "pts_win": 2, "season": "1928-29", "competition": {"type":"league_series","level": 3, "series" :2, "league": "2. Division Series 2"}, "promoted": true},
                {"place": 2, "team": "UESH", "w":  9, "d": 2, "l":  3, "f": 38, "a": 17, "pts_win": 2, "season": "1928-29", "competition": {"type":"league_series","level": 3, "series" :2, "league": "2. Division Series 2"}},
                {"place": 3, "team": "UNAS", "w":  8, "d": 3, "l":  3, "f": 39, "a": 20, "pts_win": 2, "season": "1928-29", "competition": {"type":"league_series","level": 3, "series" :2, "league": "2. Division Series 2"}},
                {"place": 4, "team": "CROD", "w":  8, "d": 3, "l":  3, "f": 38, "a": 20, "pts_win": 2, "season": "1928-29", "competition": {"type":"league_series","level": 3, "series" :2, "league": "2. Division Series 2"}},
                {"place": 5, "team": "STET", "w":  7, "d": 0, "l":  7, "f": 38, "a": 37, "pts_win": 2, "season": "1928-29", "competition": {"type":"league_series","level": 3, "series" :2, "league": "2. Division Series 2"}},
                {"place": 6, "team": "ASLX", "w":  4, "d": 0, "l": 10, "f": 34, "a": 60, "pts_win": 2, "season": "1928-29", "competition": {"type":"league_series","level": 3, "series" :2, "league": "2. Division Series 2"}},
                {"place": 7, "team": "JKYL", "w":  3, "d": 2, "l":  9, "f": 27, "a": 49, "pts_win": 2, "season": "1928-29", "competition": {"type":"league_series","level": 3, "series" :2, "league": "2. Division Series 2"}},
                {"place": 8, "team": "RPDN", "w":  1, "d": 0, "l": 13, "f": 12, "a": 50, "pts_win": 2, "season": "1928-29", "competition": {"type":"league_series","level": 3, "series" :2, "league": "2. Division Series 2"}, "relegated": true}
            ]
        }]
    },{
        "level": 4,
        "name": "3. Division",
        "pts_win": 2,
        "standings": [
            {"place": 1, "team": "OYMP", "w": 6, "d": 3, "l": 1, "f": 26, "a": 15, "pts_win": 2, "season": "1928-29", "competition": {"type":"league","level": 4, "league": "3. Division"}, "promoted": true},
            {"place": 2, "team": "WALF", "w": 6, "d": 1, "l": 3, "f": 30, "a": 20, "pts_win": 2, "season": "1928-29", "competition": {"type":"league","level": 4, "league": "3. Division"}, "promoted": true},
            {"place": 3, "team": "JHTC", "w": 4, "d": 3, "l": 3, "f": 29, "a": 24, "pts_win": 2, "season": "1928-29", "competition": {"type":"league","level": 4, "league": "3. Division"}},
            {"place": 4, "team": "MARM", "w": 4, "d": 3, "l": 3, "f": 37, "a": 24, "pts_win": 2, "season": "1928-29", "competition": {"type":"league","level": 4, "league": "3. Division"}},
            {"place": 5, "team": "JWIL", "w": 2, "d": 1, "l": 7, "f": 23, "a": 51, "pts_win": 2, "season": "1928-29", "competition": {"type":"league","level": 4, "league": "3. Division"}},
            {"place": 6, "team": "RSML", "w": 1, "d": 3, "l": 6, "f": 22, "a": 33, "pts_win": 2, "season": "1928-29", "competition": {"type":"league","level": 4, "league": "3. Division"}}
        ]
    }],
    "cup": {
        "luxembourg": {
            "name": "Luxembourg Cup",
            "rounds": [{
                "name": "Preliminary round",
                "matches": [
                    {"date":"1928-10-07", "season": "1928-29","competition": {"type":"cup","cup_code":"luxembourg","cup":"Luxembourg Cup","round":"Preliminary round","round_code":"PR"},"home": "SWFT", "homeDivision": 2,"away": "CPET", "awayDivision": 2,"score":"4-2"},
                    {"date":"1928-10-07", "season": "1928-29","competition": {"type":"cup","cup_code":"luxembourg","cup":"Luxembourg Cup","round":"Preliminary round","round_code":"PR"},"home": "PROG", "homeDivision": 2,"away": "ARIS", "awayDivision": 2,"score":"1-1","replay": {"date":"1928-11-04","score":"2-3"}},
                    {"date":"1928-10-07", "season": "1928-29","competition": {"type":"cup","cup_code":"luxembourg","cup":"Luxembourg Cup","round":"Preliminary round","round_code":"PR"},"home": "USDD", "homeDivision": 2,"away": "CROD", "awayDivision": 3,"score":"3-0","forfeit":true},
                    {"date":"1928-10-07", "season": "1928-29","competition": {"type":"cup","cup_code":"luxembourg","cup":"Luxembourg Cup","round":"Preliminary round","round_code":"PR"},"home": "UESH", "homeDivision": 3,"away": "JHTC", "awayDivision": 4,"score":"5-0"},
                    {"date":"1928-10-07", "season": "1928-29","competition": {"type":"cup","cup_code":"luxembourg","cup":"Luxembourg Cup","round":"Preliminary round","round_code":"PR"},"home": "ULUX", "homeDivision": 2,"away": "ADUD", "awayDivision": 2,"score":"7-1"}
                ]
            },{
                "name": "1st Round",
                "matches": [
                    {"date": "1928-12-02", "season": "1928-29","competition": {"type":"cup","cup_code":"luxembourg","cup":"Luxembourg Cup","round":"1st Round","round_code":"R1"},"home": "RBPF", "homeDivision": 1,"away": "ADUD", "awayDivision": 2,"score":"4-0"},
                    {"date": "1928-12-02", "season": "1928-29","competition": {"type":"cup","cup_code":"luxembourg","cup":"Luxembourg Cup","round":"1st Round","round_code":"R1"},"home": "SPOR", "homeDivision": 1,"away": "ARIS", "awayDivision": 2,"score":"5-1"},
                    {"date": "1928-12-02", "season": "1928-29","competition": {"type":"cup","cup_code":"luxembourg","cup":"Luxembourg Cup","round":"1st Round","round_code":"R1"},"home": "FOLA", "homeDivision": 1,"away": "SWFT", "awayDivision": 2,"score":"6-3"},
                    {"date": "1928-12-02", "season": "1928-29","competition": {"type":"cup","cup_code":"luxembourg","cup":"Luxembourg Cup","round":"1st Round","round_code":"R1"},"home": "JESH", "homeDivision": 1,"away": "USDD", "awayDivision": 2,"score":"4-4","replay": {"date":"1929-02-03","score":"3-2"}},
                    {"date": "1928-12-02", "season": "1928-29","competition": {"type":"cup","cup_code":"luxembourg","cup":"Luxembourg Cup","round":"1st Round","round_code":"R1"},"home": "PRON", "homeDivision": 1,"away": "ULUX", "awayDivision": 2,"score":"2-0"},
                    {"date": "1928-12-02", "season": "1928-29","competition": {"type":"cup","cup_code":"luxembourg","cup":"Luxembourg Cup","round":"1st Round","round_code":"R1"},"home": "RBDF", "homeDivision": 1,"away": "CPET", "awayDivision": 2,"score":"13-2"},
                    {"date": "1928-12-02", "season": "1928-29","competition": {"type":"cup","cup_code":"luxembourg","cup":"Luxembourg Cup","round":"1st Round","round_code":"R1"},"home": "SDUD", "homeDivision": 1,"away": "UESH", "awayDivision": 3,"score":"2-0"},
                    {"date": "1928-12-02", "season": "1928-29","competition": {"type":"cup","cup_code":"luxembourg","cup":"Luxembourg Cup","round":"1st Round","round_code":"R1"},"home": "ASDF", "homeDivision": 1,"away": "JHTC", "awayDivision": 4,"score":"3-1"}
                ]
            },{
                "name": "Quarter Final",
                "matches": [
                    {"date":"1929-03-10","season": "1928-29","competition": {"type":"cup","cup_code":"luxembourg","cup":"Luxembourg Cup","round":"Quarter Final","round_code":"QF"},"home": "FOLA", "homeDivision": 1,"away": "SPOR", "awayDivision": 1,"score":"0-3", "forfeit":true},
                    {"date":"1929-03-10","season": "1928-29","competition": {"type":"cup","cup_code":"luxembourg","cup":"Luxembourg Cup","round":"Quarter Final","round_code":"QF"},"home": "SDUD", "homeDivision": 1,"away": "RBDF", "awayDivision": 1,"score":"0-8"},
                    {"date":"1929-03-10","season": "1928-29","competition": {"type":"cup","cup_code":"luxembourg","cup":"Luxembourg Cup","round":"Quarter Final","round_code":"QF"},"home": "ASDF", "homeDivision": 1,"away": "JESH", "awayDivision": 1,"score":"2-5"},
                    {"date":"1929-03-10","season": "1928-29","competition": {"type":"cup","cup_code":"luxembourg","cup":"Luxembourg Cup","round":"Quarter Final","round_code":"QF"},"home": "RBPF", "homeDivision": 1,"away": "PRON", "awayDivision": 1,"score":"0-2"}
                ]
            },{
                "name": "Semi Final",
                "matches": [
                    {"date":"1929-04-07","season": "1928-29","competition": {"type":"cup","cup_code":"luxembourg","cup":"Luxembourg Cup","round":"Semi Final","round_code":"SF"},"home": "RBDF", "homeDivision": 1,"away": "PRON", "awayDivision": 1,"score":"5-1"},
                    {"date":"1929-04-21","season": "1928-29","competition": {"type":"cup","cup_code":"luxembourg","cup":"Luxembourg Cup","round":"Semi Final","round_code":"SF"},"home": "SPOR", "homeDivision": 1,"away": "JESH", "awayDivision": 1,"score":"5-0"}
                ]
            },{
                "name": "Final",
                "matches": [
                    {"date":"1929-06-23", "season": "1928-29","competition": {"type":"cup","cup_code":"luxembourg","cup":"Luxembourg Cup","round":"Final","round_code":"F"},"home": "SPOR", "homeDivision": 1,"away": "RBDF", "awayDivision": 1,"score":"3-5"}
                ]
            }]
        }
    }
}